scripts/__init__.py
scripts/__main__.py
scripts/docker.py
scripts/linux_service.py
scripts/nginx_config.py
scripts/ssl_manager.py
starco_scripts-1.0.6.dist-info/METADATA
starco_scripts-1.0.6.dist-info/WHEEL
starco_scripts-1.0.6.dist-info/entry_points.txt
starco_scripts-1.0.6.dist-info/top_level.txt
starco_scripts-1.0.6.dist-info/RECORD
