Metadata-Version: 2.1
Name: starco-scripts
Version: 1.0.6
Summary: Starco scripts package
Author-email: Mojtaba Tahmasbi <m.tahmasbi0111@yahoo.com>
Requires-Python: >=3.6
Requires-Dist: tqdm
Requires-Dist: colorama
Requires-Dist: rich
Requires-Dist: docker
Requires-Dist: aiohttp
